thonnycontrib/thonny-pydiderot-plugin/__init__.py
thonny_pydiderot_plugin-0.0.3.dist-info/LICENSE
thonny_pydiderot_plugin-0.0.3.dist-info/METADATA
thonny_pydiderot_plugin-0.0.3.dist-info/WHEEL
thonny_pydiderot_plugin-0.0.3.dist-info/top_level.txt
thonny_pydiderot_plugin-0.0.3.dist-info/RECORD
